{
  "formatVersion": 1,
  "database": {
    "version": 2,
    "identityHash": "a6396cea8908ab7b7a443f7890b8a3f7",
    "entities": [
      {
        "tableName": "Game",
        "createSql": "CREATE TABLE IF NOT EXISTS `${TABLE_NAME}` (`game_id` TEXT NOT NULL, `number_of_columns` INTEGER NOT NULL, `number_of_players` INTEGER NOT NULL, PRIMARY KEY(`game_id`))",
        "fields": [
          {
            "fieldPath": "gameId",
            "columnName": "game_id",
            "affinity": "TEXT",
            "notNull": true
          },
          {
            "fieldPath": "numberOfColumns",
            "columnName": "number_of_columns",
            "affinity": "INTEGER",
            "notNull": true
          },
          {
            "fieldPath": "numberOfPlayers",
            "columnName": "number_of_players",
            "affinity": "INTEGER",
            "notNull": true
          }
        ],
        "primaryKey": {
          "columnNames": [
            "game_id"
          ],
          "autoGenerate": false
        },
        "indices": [],
        "foreignKeys": []
      },
      {
        "tableName": "Player",
        "createSql": "CREATE TABLE IF NOT EXISTS `${TABLE_NAME}` (`player_id` TEXT NOT NULL, `played_game_id` TEXT NOT NULL, `name` TEXT NOT NULL, `score_column_one` INTEGER, `has_won_column_one` INTEGER, `score_column_two` INTEGER, `has_won_column_two` INTEGER, `score_column_three` INTEGER, `has_won_column_three` INTEGER, PRIMARY KEY(`player_id`))",
        "fields": [
          {
            "fieldPath": "playerId",
            "columnName": "player_id",
            "affinity": "TEXT",
            "notNull": true
          },
          {
            "fieldPath": "playedGameId",
            "columnName": "played_game_id",
            "affinity": "TEXT",
            "notNull": true
          },
          {
            "fieldPath": "name",
            "columnName": "name",
            "affinity": "TEXT",
            "notNull": true
          },
          {
            "fieldPath": "score.scoreColumnOne",
            "columnName": "score_column_one",
            "affinity": "INTEGER",
            "notNull": false
          },
          {
            "fieldPath": "score.hasWonColumnOne",
            "columnName": "has_won_column_one",
            "affinity": "INTEGER",
            "notNull": false
          },
          {
            "fieldPath": "score.scoreColumnTwo",
            "columnName": "score_column_two",
            "affinity": "INTEGER",
            "notNull": false
          },
          {
            "fieldPath": "score.hasWonColumnTwo",
            "columnName": "has_won_column_two",
            "affinity": "INTEGER",
            "notNull": false
          },
          {
            "fieldPath": "score.scoreColumnThree",
            "columnName": "score_column_three",
            "affinity": "INTEGER",
            "notNull": false
          },
          {
            "fieldPath": "score.hasWonColumnThree",
            "columnName": "has_won_column_three",
            "affinity": "INTEGER",
            "notNull": false
          }
        ],
        "primaryKey": {
          "columnNames": [
            "player_id"
          ],
          "autoGenerate": false
        },
        "indices": [],
        "foreignKeys": []
      }
    ],
    "views": [],
    "setupQueries": [
      "CREATE TABLE IF NOT EXISTS room_master_table (id INTEGER PRIMARY KEY,identity_hash TEXT)",
      "INSERT OR REPLACE INTO room_master_table (id,identity_hash) VALUES(42, 'a6396cea8908ab7b7a443f7890b8a3f7')"
    ]
  }
}